Workbook

Sheet Datos_Pronostico
A1: ContaFacil - Ingresos mensuales por honorarios (datos FICTICIOS para pruebas)
A3: Periodo | B3: Ingresos (₡) | D3: Nota:
A4: 45200 | B4: =Ingresos_Mensuales!C4 -> 1328649 | D4: Esta es la hoja que se importa/pega en la herramienta (A = periodo, B = valor). Montos sin IVA.
A5: 45231 | B5: =Ingresos_Mensuales!C5 -> 1307139 | D5: Los ingresos salen de la facturación detallada (horas x tarifa del catálogo CCPA). Ver hoja Supuestos_Fuentes.
A6: 45261 | B6: =Ingresos_Mensuales!C6 -> 1839173
A7: 45292 | B7: =Ingresos_Mensuales!C7 -> 1708672
A8: 45323 | B8: =Ingresos_Mensuales!C8 -> 1523683
A9: 45352 | B9: =Ingresos_Mensuales!C9 -> 1825549
A10: 45383 | B10: =Ingresos_Mensuales!C10 -> 1335820
A11: 45413 | B11: =Ingresos_Mensuales!C11 -> 1489262
A12: 45444 | B12: =Ingresos_Mensuales!C12 -> 1307138
A13: 45474 | B13: =Ingresos_Mensuales!C13 -> 1648442
A14: 45505 | B14: =Ingresos_Mensuales!C14 -> 1342990
A15: 45536 | B15: =Ingresos_Mensuales!C15 -> 1307138
A16: 45566 | B16: =Ingresos_Mensuales!C16 -> 1393182
A17: 45597 | B17: =Ingresos_Mensuales!C17 -> 1386011
... A39: 46266 | B39: =Ingresos_Mensuales!C39 -> 1540888

Sheet Ingresos_Mensuales
A1: Resumen mensual: ingresos, clientes activos, declaraciones y horas facturadas
A3: Año | B3: Mes | C3: Ingresos totales (₡) | D3: Clientes activos | E3: Declaraciones presentadas | F3: Horas facturadas | G3: Ingreso Cliente C01 (₡) | H3: % C01 sobre total
A4: 2023 | B4: Octubre | C4: =Detalle_Clientes!N4 -> 1328649 | D4: =COUNTIF(Detalle_Clientes!B4:M4,">0") -> 8 | E4: =Declaraciones!G4 -> 15 | F4: =SUMIFS(Facturacion!$F$4:$F$724,Facturacion!$A$4:$A$724,Detalle_Clientes!A4) -> 46.25 | G4: =Detalle_Clientes!B4 -> 688344 | H4: =G4/C4 -> 0.51807814
A5: 2023 | B5: Noviembre | C5: =Detalle_Clientes!N5 -> 1307139 | D5: =COUNTIF(Detalle_Clientes!B5:M5,">0") -> 8 | E5: =Declaraciones!G5 -> 15 | F5: =SUMIFS(Facturacion!$F$4:$F$724,Facturacion!$A$4:$A$724,Detalle_Clientes!A5) -> 45.5 | G5: =Detalle_Clientes!B5 -> 702685 | H5: =G5/C5 -> 0.53757481
A6: 2023 | B6: Diciembre | C6: =Detalle_Clientes!N6 -> 1839173 | D6: =COUNTIF(Detalle_Clientes!B6:M6,">0") -> 8 | E6: =Declaraciones!G6 -> 20 | F6: =SUMIFS(Facturacion!$F$4:$F$724,Facturacion!$A$4:$A$724,Detalle_Clientes!A6) -> 63.75 | G6: =Detalle_Clientes!B6 -> 989495 | H6: =G6/C6 -> 0.53801083
A7: 2024 | B7: Enero | C7: =Detalle_Clientes!N7 -> 1708672 | D7: =COUNTIF(Detalle_Clientes!B7:M7,">0") -> 8 | E7: =Declaraciones!G7 -> 18 | F7: =SUMIFS(Facturacion!$F$4:$F$724,Facturacion!$A$4:$A$724,Detalle_Clientes!A7) -> 59.5 | G7: =Detalle_Clientes!B7 -> 774387 | H7: =G7/C7 -> 0.45320986
A8: 2024 | B8: Febrero | C8: =Detalle_Clientes!N8 -> 1523683 | D8: =COUNTIF(Detalle_Clientes!B8:M8,">0") -> 9 | E8: =Declaraciones!G8 -> 23 | F8: =SUMIFS(Facturacion!$F$4:$F$724,Facturacion!$A$4:$A$724,Detalle_Clientes!A8) -> 53 | G8: =Detalle_Clientes!B8 -> 760047 | H8: =G8/C8 -> 0.49882226
A9: 2024 | B9: Marzo | C9: =Detalle_Clientes!N9 -> 1825549 | D9: =COUNTIF(Detalle_Clientes!B9:M9,">0") -> 11 | E9: =Declaraciones!G9 -> 21 | F9: =SUMIFS(Facturacion!$F$4:$F$724,Facturacion!$A$4:$A$724,Detalle_Clientes!A9) -> 63 | G9: =Detalle_Clientes!B9 -> 717025 | H9: =G9/C9 -> 0.39277226
A10: 2024 | B10: Abril | C10: =Detalle_Clientes!N10 -> 1335820 | D10: =COUNTIF(Detalle_Clientes!B10:M10,">0") -> 8 | E10: =Declaraciones!G10 -> 15 | F10: =SUMIFS(Facturacion!$F$4:$F$724,Facturacion!$A$4:$A$724,Detalle_Clientes!A10) -> 46.5 | G10: =Detalle_Clientes!B10 -> 674004 | H10: =G10/C10 -> 0.50456199
A11: 2024 | B11: Mayo | C11: =Detalle_Clientes!N11 -> 1489262 | D11: =COUNTIF(Detalle_Clientes!B11:M11,">0") -> 8 | E11: =Declaraciones!G11 -> 15 | F11: =SUMIFS(Facturacion!$F$4:$F$724,Facturacion!$A$4:$A$724,Detalle_Clientes!A11) -> 51.75 | G11: =Detalle_Clientes!B11 -> 745706 | H11: =G11/C11 -> 0.50072183
A12: 2024 | B12: Junio | C12: =Detalle_Clientes!N12 -> 1307138 | D12: =COUNTIF(Detalle_Clientes!B12:M12,">0") -> 8 | E12: =Declaraciones!G12 -> 15 | F12: =SUMIFS(Facturacion!$F$4:$F$724,Facturacion!$A$4:$A$724,Detalle_Clientes!A12) -> 45.5 | G12: =Detalle_Clientes!B12 -> 688344 | H12: =G12/C12 -> 0.52660392
A13: 2024 | B13: Julio | C13: =Detalle_Clientes!N13 -> 1648442 | D13: =COUNTIF(Detalle_Clientes!B13:M13,">0") -> 9 | E13: =Declaraciones!G13 -> 15 | F13: =SUMIFS(Facturacion!$F$4:$F$724,Facturacion!$A$4:$A$724,Detalle_Clientes!A13) -> 57.25 | G13: =Detalle_Clientes!B13 -> 989495 | H13: =G13/C13 -> 0.60026073
A14: 2024 | B14: Agosto | C14: =Detalle_Clientes!N14 -> 1342990 | D14: =COUNTIF(Detalle_Clientes!B14:M14,">0") -> 8 | E14: =Declaraciones!G14 -> 15 | F14: =SUMIFS(Facturacion!$F$4:$F$724,Facturacion!$A$4:$A$724,Detalle_Clientes!A14) -> 46.75 | G14: =Detalle_Clientes!B14 -> 731366 | H14: =G14/C14 -> 0.54458038
A15: 2024 | B15: Septiembre | C15: =Detalle_Clientes!N15 -> 1307138 | D15: =COUNTIF(Detalle_Clientes!B15:M15,">0") -> 8 | E15: =Declaraciones!G15 -> 15 | F15: =SUMIFS(Facturacion!$F$4:$F$724,Facturacion!$A$4:$A$724,Detalle_Clientes!A15) -> 45.5 | G15: =Detalle_Clientes!B15 -> 688344 | H15: =G15/C15 -> 0.52660392
... A39: 2026 | B39: Septiembre | C39: =Detalle_Clientes!N39 -> 1540888 | D39: =COUNTIF(Detalle_Clientes!B39:M39,">0") -> 9 | E39: =Declaraciones!G39 -> 15 | F39: =SUMIFS(Facturacion!$F$4:$F$724,Facturacion!$A$4:$A$724,Detalle_Clientes!A39) -> 53.5 | G39: =Detalle_Clientes!B39 -> 788728 | H39: =G39/C39 -> 0.51186589

Sheet Detalle_Clientes
A1: Ingresos por cliente y mes (₡, sin IVA) - calculados desde la hoja Facturacion
A2: Cód. | B2: C01 | C2: C02 | D2: C03 | E2: C04 | F2: C05 | G2: C06 | H2: C07 | I2: C08 | J2: C09 | K2: C10 | L2: C11 | M2: C12
A3: Periodo | B3: Distribuidora Los Andes S.A. | C3: Ferretería El Tornillo | D3: Clínica Dental Sonrisa | E3: Soda y Restaurante Doña Lela | F3: Transportes Rápidos del Valle | G3: Boutique Luna Nueva | H3: Taller Mecánico Hermanos Mora | I3: Agroservicios Cartago | J3: Estudio Fotográfico Lumière | K3: Panadería La Espiga | L3: Consultores TIC Pura Vida | M3: Veterinaria Mascotas Felices | N3: TOTAL
A4: 45200 | B4: =SUMIFS(Facturacion!$I$4:$I$724,Facturacion!$A$4:$A$724,$A4,Facturacion!$B$4:$B$724,B$2) -> 688344 | C4: =SUMIFS(Facturacion!$I$4:$I$724,Facturacion!$A$4:$A$724,$A4,Facturacion!$B$4:$B$724,C$2) -> 107554 | D4: =SUMIFS(Facturacion!$I$4:$I$724,Facturacion!$A$4:$A$724,$A4,Facturacion!$B$4:$B$724,D$2) -> 23662 | E4: =SUMIFS(Facturacion!$I$4:$I$724,Facturacion!$A$4:$A$724,$A4,Facturacion!$B$4:$B$724,E$2) -> 21511 | F4: =SUMIFS(Facturacion!$I$4:$I$724,Facturacion!$A$4:$A$724,$A4,Facturacion!$B$4:$B$724,F$2) -> 215108 | G4: =SUMIFS(Facturacion!$I$4:$I$724,Facturacion!$A$4:$A$724,$A4,Facturacion!$B$4:$B$724,G$2) -> 0 | H4: =SUMIFS(Facturacion!$I$4:$I$724,Facturacion!$A$4:$A$724,$A4,Facturacion!$B$4:$B$724,H$2) -> 21511 | I4: =SUMIFS(Facturacion!$I$4:$I$724,Facturacion!$A$4:$A$724,$A4,Facturacion!$B$4:$B$724,I$2) -> 28681 | ... M4: =SUMIFS(Facturacion!$I$4:$I$724,Facturacion!$A$4:$A$724,$A4,Facturacion!$B$4:$B$724,M$2) -> 0 | N4: =SUM(B4:M4) -> 1328649
A5: 45231 | B5: =SUMIFS(Facturacion!$I$4:$I$724,Facturacion!$A$4:$A$724,$A5,Facturacion!$B$4:$B$724,B$2) -> 702685 | C5: =SUMIFS(Facturacion!$I$4:$I$724,Facturacion!$A$4:$A$724,$A5,Facturacion!$B$4:$B$724,C$2) -> 114724 | D5: =SUMIFS(Facturacion!$I$4:$I$724,Facturacion!$A$4:$A$724,$A5,Facturacion!$B$4:$B$724,D$2) -> 23662 | E5: =SUMIFS(Facturacion!$I$4:$I$724,Facturacion!$A$4:$A$724,$A5,Facturacion!$B$4:$B$724,E$2) -> 21511 | F5: =SUMIFS(Facturacion!$I$4:$I$724,Facturacion!$A$4:$A$724,$A5,Facturacion!$B$4:$B$724,F$2) -> 186427 | G5: =SUMIFS(Facturacion!$I$4:$I$724,Facturacion!$A$4:$A$724,$A5,Facturacion!$B$4:$B$724,G$2) -> 0 | H5: =SUMIFS(Facturacion!$I$4:$I$724,Facturacion!$A$4:$A$724,$A5,Facturacion!$B$4:$B$724,H$2) -> 21511 | I5: =SUMIFS(Facturacion!$I$4:$I$724,Facturacion!$A$4:$A$724,$A5,Facturacion!$B$4:$B$724,I$2) -> 28681 | ... M5: =SUMIFS(Facturacion!$I$4:$I$724,Facturacion!$A$4:$A$724,$A5,Facturacion!$B$4:$B$724,M$2) -> 0 | N5: =SUM(B5:M5) -> 1307139
A6: 45261 | B6: =SUMIFS(Facturacion!$I$4:$I$724,Facturacion!$A$4:$A$724,$A6,Facturacion!$B$4:$B$724,B$2) -> 989495 | C6: =SUMIFS(Facturacion!$I$4:$I$724,Facturacion!$A$4:$A$724,$A6,Facturacion!$B$4:$B$724,C$2) -> 121894 | D6: =SUMIFS(Facturacion!$I$4:$I$724,Facturacion!$A$4:$A$724,$A6,Facturacion!$B$4:$B$724,D$2) -> 118310 | E6: =SUMIFS(Facturacion!$I$4:$I$724,Facturacion!$A$4:$A$724,$A6,Facturacion!$B$4:$B$724,E$2) -> 64533 | F6: =SUMIFS(Facturacion!$I$4:$I$724,Facturacion!$A$4:$A$724,$A6,Facturacion!$B$4:$B$724,F$2) -> 229449 | G6: =SUMIFS(Facturacion!$I$4:$I$724,Facturacion!$A$4:$A$724,$A6,Facturacion!$B$4:$B$724,G$2) -> 0 | H6: =SUMIFS(Facturacion!$I$4:$I$724,Facturacion!$A$4:$A$724,$A6,Facturacion!$B$4:$B$724,H$2) -> 21511 | I6: =SUMIFS(Facturacion!$I$4:$I$724,Facturacion!$A$4:$A$724,$A6,Facturacion!$B$4:$B$724,I$2) -> 28681 | ... M6: =SUMIFS(Facturacion!$I$4:$I$724,Facturacion!$A$4:$A$724,$A6,Facturacion!$B$4:$B$724,M$2) -> 0 | N6: =SUM(B6:M6) -> 1839173
A7: 45292 | B7: =SUMIFS(Facturacion!$I$4:$I$724,Facturacion!$A$4:$A$724,$A7,Facturacion!$B$4:$B$724,B$2) -> 774387 | C7: =SUMIFS(Facturacion!$I$4:$I$724,Facturacion!$A$4:$A$724,$A7,Facturacion!$B$4:$B$724,C$2) -> 114724 | D7: =SUMIFS(Facturacion!$I$4:$I$724,Facturacion!$A$4:$A$724,$A7,Facturacion!$B$4:$B$724,D$2) -> 23662 | E7: =SUMIFS(Facturacion!$I$4:$I$724,Facturacion!$A$4:$A$724,$A7,Facturacion!$B$4:$B$724,E$2) -> 21511 | F7: =SUMIFS(Facturacion!$I$4:$I$724,Facturacion!$A$4:$A$724,$A7,Facturacion!$B$4:$B$724,F$2) -> 430215 | G7: =SUMIFS(Facturacion!$I$4:$I$724,Facturacion!$A$4:$A$724,$A7,Facturacion!$B$4:$B$724,G$2) -> 0 | H7: =SUMIFS(Facturacion!$I$4:$I$724,Facturacion!$A$4:$A$724,$A7,Facturacion!$B$4:$B$724,H$2) -> 21511 | I7: =SUMIFS(Facturacion!$I$4:$I$724,Facturacion!$A$4:$A$724,$A7,Facturacion!$B$4:$B$724,I$2) -> 28681 | ... M7: =SUMIFS(Facturacion!$I$4:$I$724,Facturacion!$A$4:$A$724,$A7,Facturacion!$B$4:$B$724,M$2) -> 0 | N7: =SUM(B7:M7) -> 1708672
A8: 45323 | B8: =SUMIFS(Facturacion!$I$4:$I$724,Facturacion!$A$4:$A$724,$A8,Facturacion!$B$4:$B$724,B$2) -> 760047 | C8: =SUMIFS(Facturacion!$I$4:$I$724,Facturacion!$A$4:$A$724,$A8,Facturacion!$B$4:$B$724,C$2) -> 129065 | D8: =SUMIFS(Facturacion!$I$4:$I$724,Facturacion!$A$4:$A$724,$A8,Facturacion!$B$4:$B$724,D$2) -> 39437 | E8: =SUMIFS(Facturacion!$I$4:$I$724,Facturacion!$A$4:$A$724,$A8,Facturacion!$B$4:$B$724,E$2) -> 35852 | F8: =SUMIFS(Facturacion!$I$4:$I$724,Facturacion!$A$4:$A$724,$A8,Facturacion!$B$4:$B$724,F$2) -> 215108 | G8: =SUMIFS(Facturacion!$I$4:$I$724,Facturacion!$A$4:$A$724,$A8,Facturacion!$B$4:$B$724,G$2) -> 0 | H8: =SUMIFS(Facturacion!$I$4:$I$724,Facturacion!$A$4:$A$724,$A8,Facturacion!$B$4:$B$724,H$2) -> 35852 | I8: =SUMIFS(Facturacion!$I$4:$I$724,Facturacion!$A$4:$A$724,$A8,Facturacion!$B$4:$B$724,I$2) -> 43022 | ... M8: =SUMIFS(Facturacion!$I$4:$I$724,Facturacion!$A$4:$A$724,$A8,Facturacion!$B$4:$B$724,M$2) -> 0 | N8: =SUM(B8:M8) -> 1523683
A9: 45352 | B9: =SUMIFS(Facturacion!$I$4:$I$724,Facturacion!$A$4:$A$724,$A9,Facturacion!$B$4:$B$724,B$2) -> 717025 | C9: =SUMIFS(Facturacion!$I$4:$I$724,Facturacion!$A$4:$A$724,$A9,Facturacion!$B$4:$B$724,C$2) -> 337002 | D9: =SUMIFS(Facturacion!$I$4:$I$724,Facturacion!$A$4:$A$724,$A9,Facturacion!$B$4:$B$724,D$2) -> 23662 | E9: =SUMIFS(Facturacion!$I$4:$I$724,Facturacion!$A$4:$A$724,$A9,Facturacion!$B$4:$B$724,E$2) -> 21511 | F9: =SUMIFS(Facturacion!$I$4:$I$724,Facturacion!$A$4:$A$724,$A9,Facturacion!$B$4:$B$724,F$2) -> 172086 | G9: =SUMIFS(Facturacion!$I$4:$I$724,Facturacion!$A$4:$A$724,$A9,Facturacion!$B$4:$B$724,G$2) -> 49475 | H9: =SUMIFS(Facturacion!$I$4:$I$724,Facturacion!$A$4:$A$724,$A9,Facturacion!$B$4:$B$724,H$2) -> 64533 | I9: =SUMIFS(Facturacion!$I$4:$I$724,Facturacion!$A$4:$A$724,$A9,Facturacion!$B$4:$B$724,I$2) -> 78873 | ... M9: =SUMIFS(Facturacion!$I$4:$I$724,Facturacion!$A$4:$A$724,$A9,Facturacion!$B$4:$B$724,M$2) -> 0 | N9: =SUM(B9:M9) -> 1825549
A10: 45383 | B10: =SUMIFS(Facturacion!$I$4:$I$724,Facturacion!$A$4:$A$724,$A10,Facturacion!$B$4:$B$724,B$2) -> 674004 | C10: =SUMIFS(Facturacion!$I$4:$I$724,Facturacion!$A$4:$A$724,$A10,Facturacion!$B$4:$B$724,C$2) -> 114724 | D10: =SUMIFS(Facturacion!$I$4:$I$724,Facturacion!$A$4:$A$724,$A10,Facturacion!$B$4:$B$724,D$2) -> 23662 | E10: =SUMIFS(Facturacion!$I$4:$I$724,Facturacion!$A$4:$A$724,$A10,Facturacion!$B$4:$B$724,E$2) -> 21511 | F10: =SUMIFS(Facturacion!$I$4:$I$724,Facturacion!$A$4:$A$724,$A10,Facturacion!$B$4:$B$724,F$2) -> 186427 | G10: =SUMIFS(Facturacion!$I$4:$I$724,Facturacion!$A$4:$A$724,$A10,Facturacion!$B$4:$B$724,G$2) -> 0 | H10: =SUMIFS(Facturacion!$I$4:$I$724,Facturacion!$A$4:$A$724,$A10,Facturacion!$B$4:$B$724,H$2) -> 21511 | I10: =SUMIFS(Facturacion!$I$4:$I$724,Facturacion!$A$4:$A$724,$A10,Facturacion!$B$4:$B$724,I$2) -> 28681 | ... M10: =SUMIFS(Facturacion!$I$4:$I$724,Facturacion!$A$4:$A$724,$A10,Facturacion!$B$4:$B$724,M$2) -> 0 | N10: =SUM(B10:M10) -> 1335820
A11: 45413 | B11: =SUMIFS(Facturacion!$I$4:$I$724,Facturacion!$A$4:$A$724,$A11,Facturacion!$B$4:$B$724,B$2) -> 745706 | C11: =SUMIFS(Facturacion!$I$4:$I$724,Facturacion!$A$4:$A$724,$A11,Facturacion!$B$4:$B$724,C$2) -> 121894 | D11: =SUMIFS(Facturacion!$I$4:$I$724,Facturacion!$A$4:$A$724,$A11,Facturacion!$B$4:$B$724,D$2) -> 55211 | E11: =SUMIFS(Facturacion!$I$4:$I$724,Facturacion!$A$4:$A$724,$A11,Facturacion!$B$4:$B$724,E$2) -> 21511 | F11: =SUMIFS(Facturacion!$I$4:$I$724,Facturacion!$A$4:$A$724,$A11,Facturacion!$B$4:$B$724,F$2) -> 186427 | G11: =SUMIFS(Facturacion!$I$4:$I$724,Facturacion!$A$4:$A$724,$A11,Facturacion!$B$4:$B$724,G$2) -> 0 | H11: =SUMIFS(Facturacion!$I$4:$I$724,Facturacion!$A$4:$A$724,$A11,Facturacion!$B$4:$B$724,H$2) -> 107554 | I11: =SUMIFS(Facturacion!$I$4:$I$724,Facturacion!$A$4:$A$724,$A11,Facturacion!$B$4:$B$724,I$2) -> 28681 | ... M11: =SUMIFS(Facturacion!$I$4:$I$724,Facturacion!$A$4:$A$724,$A11,Facturacion!$B$4:$B$724,M$2) -> 0 | N11: =SUM(B11:M11) -> 1489262
A12: 45444 | B12: =SUMIFS(Facturacion!$I$4:$I$724,Facturacion!$A$4:$A$724,$A12,Facturacion!$B$4:$B$724,B$2) -> 688344 | C12: =SUMIFS(Facturacion!$I$4:$I$724,Facturacion!$A$4:$A$724,$A12,Facturacion!$B$4:$B$724,C$2) -> 114724 | D12: =SUMIFS(Facturacion!$I$4:$I$724,Facturacion!$A$4:$A$724,$A12,Facturacion!$B$4:$B$724,D$2) -> 23662 | E12: =SUMIFS(Facturacion!$I$4:$I$724,Facturacion!$A$4:$A$724,$A12,Facturacion!$B$4:$B$724,E$2) -> 21511 | F12: =SUMIFS(Facturacion!$I$4:$I$724,Facturacion!$A$4:$A$724,$A12,Facturacion!$B$4:$B$724,F$2) -> 186427 | G12: =SUMIFS(Facturacion!$I$4:$I$724,Facturacion!$A$4:$A$724,$A12,Facturacion!$B$4:$B$724,G$2) -> 0 | H12: =SUMIFS(Facturacion!$I$4:$I$724,Facturacion!$A$4:$A$724,$A12,Facturacion!$B$4:$B$724,H$2) -> 21511 | I12: =SUMIFS(Facturacion!$I$4:$I$724,Facturacion!$A$4:$A$724,$A12,Facturacion!$B$4:$B$724,I$2) -> 28681 | ... M12: =SUMIFS(Facturacion!$I$4:$I$724,Facturacion!$A$4:$A$724,$A12,Facturacion!$B$4:$B$724,M$2) -> 0 | N12: =SUM(B12:M12) -> 1307138
A13: 45474 | B13: =SUMIFS(Facturacion!$I$4:$I$724,Facturacion!$A$4:$A$724,$A13,Facturacion!$B$4:$B$724,B$2) -> 989495 | C13: =SUMIFS(Facturacion!$I$4:$I$724,Facturacion!$A$4:$A$724,$A13,Facturacion!$B$4:$B$724,C$2) -> 121894 | D13: =SUMIFS(Facturacion!$I$4:$I$724,Facturacion!$A$4:$A$724,$A13,Facturacion!$B$4:$B$724,D$2) -> 23662 | E13: =SUMIFS(Facturacion!$I$4:$I$724,Facturacion!$A$4:$A$724,$A13,Facturacion!$B$4:$B$724,E$2) -> 21511 | F13: =SUMIFS(Facturacion!$I$4:$I$724,Facturacion!$A$4:$A$724,$A13,Facturacion!$B$4:$B$724,F$2) -> 200767 | G13: =SUMIFS(Facturacion!$I$4:$I$724,Facturacion!$A$4:$A$724,$A13,Facturacion!$B$4:$B$724,G$2) -> 32983 | H13: =SUMIFS(Facturacion!$I$4:$I$724,Facturacion!$A$4:$A$724,$A13,Facturacion!$B$4:$B$724,H$2) -> 21511 | I13: =SUMIFS(Facturacion!$I$4:$I$724,Facturacion!$A$4:$A$724,$A13,Facturacion!$B$4:$B$724,I$2) -> 28681 | ... M13: =SUMIFS(Facturacion!$I$4:$I$724,Facturacion!$A$4:$A$724,$A13,Facturacion!$B$4:$B$724,M$2) -> 0 | N13: =SUM(B13:M13) -> 1648442
A14: 45505 | B14: =SUMIFS(Facturacion!$I$4:$I$724,Facturacion!$A$4:$A$724,$A14,Facturacion!$B$4:$B$724,B$2) -> 731366 | C14: =SUMIFS(Facturacion!$I$4:$I$724,Facturacion!$A$4:$A$724,$A14,Facturacion!$B$4:$B$724,C$2) -> 121894 | D14: =SUMIFS(Facturacion!$I$4:$I$724,Facturacion!$A$4:$A$724,$A14,Facturacion!$B$4:$B$724,D$2) -> 23662 | E14: =SUMIFS(Facturacion!$I$4:$I$724,Facturacion!$A$4:$A$724,$A14,Facturacion!$B$4:$B$724,E$2) -> 21511 | F14: =SUMIFS(Facturacion!$I$4:$I$724,Facturacion!$A$4:$A$724,$A14,Facturacion!$B$4:$B$724,F$2) -> 186427 | G14: =SUMIFS(Facturacion!$I$4:$I$724,Facturacion!$A$4:$A$724,$A14,Facturacion!$B$4:$B$724,G$2) -> 0 | H14: =SUMIFS(Facturacion!$I$4:$I$724,Facturacion!$A$4:$A$724,$A14,Facturacion!$B$4:$B$724,H$2) -> 21511 | I14: =SUMIFS(Facturacion!$I$4:$I$724,Facturacion!$A$4:$A$724,$A14,Facturacion!$B$4:$B$724,I$2) -> 28681 | ... M14: =SUMIFS(Facturacion!$I$4:$I$724,Facturacion!$A$4:$A$724,$A14,Facturacion!$B$4:$B$724,M$2) -> 0 | N14: =SUM(B14:M14) -> 1342990
A15: 45536 | B15: =SUMIFS(Facturacion!$I$4:$I$724,Facturacion!$A$4:$A$724,$A15,Facturacion!$B$4:$B$724,B$2) -> 688344 | C15: =SUMIFS(Facturacion!$I$4:$I$724,Facturacion!$A$4:$A$724,$A15,Facturacion!$B$4:$B$724,C$2) -> 114724 | D15: =SUMIFS(Facturacion!$I$4:$I$724,Facturacion!$A$4:$A$724,$A15,Facturacion!$B$4:$B$724,D$2) -> 23662 | E15: =SUMIFS(Facturacion!$I$4:$I$724,Facturacion!$A$4:$A$724,$A15,Facturacion!$B$4:$B$724,E$2) -> 21511 | F15: =SUMIFS(Facturacion!$I$4:$I$724,Facturacion!$A$4:$A$724,$A15,Facturacion!$B$4:$B$724,F$2) -> 186427 | G15: =SUMIFS(Facturacion!$I$4:$I$724,Facturacion!$A$4:$A$724,$A15,Facturacion!$B$4:$B$724,G$2) -> 0 | H15: =SUMIFS(Facturacion!$I$4:$I$724,Facturacion!$A$4:$A$724,$A15,Facturacion!$B$4:$B$724,H$2) -> 21511 | I15: =SUMIFS(Facturacion!$I$4:$I$724,Facturacion!$A$4:$A$724,$A15,Facturacion!$B$4:$B$724,I$2) -> 28681 | ... M15: =SUMIFS(Facturacion!$I$4:$I$724,Facturacion!$A$4:$A$724,$A15,Facturacion!$B$4:$B$724,M$2) -> 0 | N15: =SUM(B15:M15) -> 1307138
... A39: 46266 | B39: =SUMIFS(Facturacion!$I$4:$I$724,Facturacion!$A$4:$A$724,$A39,Facturacion!$B$4:$B$724,B$2) -> 788728 | C39: =SUMIFS(Facturacion!$I$4:$I$724,Facturacion!$A$4:$A$724,$A39,Facturacion!$B$4:$B$724,C$2) -> 136235 | D39: =SUMIFS(Facturacion!$I$4:$I$724,Facturacion!$A$4:$A$724,$A39,Facturacion!$B$4:$B$724,D$2) -> 23662 | E39: =SUMIFS(Facturacion!$I$4:$I$724,Facturacion!$A$4:$A$724,$A39,Facturacion!$B$4:$B$724,E$2) -> 28681 | F39: =SUMIFS(Facturacion!$I$4:$I$724,Facturacion!$A$4:$A$724,$A39,Facturacion!$B$4:$B$724,F$2) -> 215108 | G39: =SUMIFS(Facturacion!$I$4:$I$724,Facturacion!$A$4:$A$724,$A39,Facturacion!$B$4:$B$724,G$2) -> 32983 | H39: =SUMIFS(Facturacion!$I$4:$I$724,Facturacion!$A$4:$A$724,$A39,Facturacion!$B$4:$B$724,H$2) -> 21511 | I39: =SUMIFS(Facturacion!$I$4:$I$724,Facturacion!$A$4:$A$724,$A39,Facturacion!$B$4:$B$724,I$2) -> 35851 | ... M39: =SUMIFS(Facturacion!$I$4:$I$724,Facturacion!$A$4:$A$724,$A39,Facturacion!$B$4:$B$724,M$2) -> 0 | N39: =SUM(B39:M39) -> 1540888

Sheet Facturacion
A1: Facturación detallada: una línea por cliente, servicio y mes
A2: Monto = horas x tarifa horaria (Parametros) x factor del cliente (Clientes). Las horas son el dato simulado; lo demás son fórmulas.
A3: Periodo | B3: Cód. cliente | C3: Cód. servicio | D3: Cliente | E3: Servicio | F3: Horas | G3: Tarifa/hora (₡) | H3: Factor cliente | I3: Monto (₡)
A4: 45200 | B4: C01 | C4: S02 | D4: =INDEX(Clientes!$B$4:$B$15,MATCH(B4,Clientes!$A$4:$A$15,0)) -> Distribuidora Los Andes S.A. | E4: =INDEX(Catalogo_Servicios!$C$4:$C$24,MATCH(C4,Catalogo_Servicios!$A$4:$A$24,0)) -> Estados financieros mensuales | F4: 3 | G4: =Parametros!$B$4 -> 28681 | H4: =INDEX(Clientes!$E$4:$E$15,MATCH(B4,Clientes!$A$4:$A$15,0)) -> 1 | I4: =ROUND(F4*G4*H4,0) -> 86043
A5: 45200 | B5: C01 | C5: S03 | D5: =INDEX(Clientes!$B$4:$B$15,MATCH(B5,Clientes!$A$4:$A$15,0)) -> Distribuidora Los Andes S.A. | E5: =INDEX(Catalogo_Servicios!$C$4:$C$24,MATCH(C5,Catalogo_Servicios!$A$4:$A$24,0)) -> Declaración mensual de IVA (D-104) | F5: 0.75 | G5: =Parametros!$B$4 -> 28681 | H5: =INDEX(Clientes!$E$4:$E$15,MATCH(B5,Clientes!$A$4:$A$15,0)) -> 1 | I5: =ROUND(F5*G5*H5,0) -> 21511
A6: 45200 | B6: C01 | C6: S04 | D6: =INDEX(Clientes!$B$4:$B$15,MATCH(B6,Clientes!$A$4:$A$15,0)) -> Distribuidora Los Andes S.A. | E6: =INDEX(Catalogo_Servicios!$C$4:$C$24,MATCH(C6,Catalogo_Servicios!$A$4:$A$24,0)) -> Declaración mensual de retenciones (D-103) | F6: 0.25 | G6: =Parametros!$B$4 -> 28681 | H6: =INDEX(Clientes!$E$4:$E$15,MATCH(B6,Clientes!$A$4:$A$15,0)) -> 1 | I6: =ROUND(F6*G6*H6,0) -> 7170
A7: 45200 | B7: C01 | C7: S05 | D7: =INDEX(Clientes!$B$4:$B$15,MATCH(B7,Clientes!$A$4:$A$15,0)) -> Distribuidora Los Andes S.A. | E7: =INDEX(Catalogo_Servicios!$C$4:$C$24,MATCH(C7,Catalogo_Servicios!$A$4:$A$24,0)) -> Cálculo de planillas y cargas sociales (CCSS/INS) | F7: 20 | G7: =Parametros!$B$4 -> 28681 | H7: =INDEX(Clientes!$E$4:$E$15,MATCH(B7,Clientes!$A$4:$A$15,0)) -> 1 | I7: =ROUND(F7*G7*H7,0) -> 573620
A8: 45200 | B8: C02 | C8: S02 | D8: =INDEX(Clientes!$B$4:$B$15,MATCH(B8,Clientes!$A$4:$A$15,0)) -> Ferretería El Tornillo | E8: =INDEX(Catalogo_Servicios!$C$4:$C$24,MATCH(C8,Catalogo_Servicios!$A$4:$A$24,0)) -> Estados financieros mensuales | F8: 2.75 | G8: =Parametros!$B$4 -> 28681 | H8: =INDEX(Clientes!$E$4:$E$15,MATCH(B8,Clientes!$A$4:$A$15,0)) -> 1 | I8: =ROUND(F8*G8*H8,0) -> 78873
A9: 45200 | B9: C02 | C9: S03 | D9: =INDEX(Clientes!$B$4:$B$15,MATCH(B9,Clientes!$A$4:$A$15,0)) -> Ferretería El Tornillo | E9: =INDEX(Catalogo_Servicios!$C$4:$C$24,MATCH(C9,Catalogo_Servicios!$A$4:$A$24,0)) -> Declaración mensual de IVA (D-104) | F9: 0.75 | G9: =Parametros!$B$4 -> 28681 | H9: =INDEX(Clientes!$E$4:$E$15,MATCH(B9,Clientes!$A$4:$A$15,0)) -> 1 | I9: =ROUND(F9*G9*H9,0) -> 21511
A10: 45200 | B10: C02 | C10: S04 | D10: =INDEX(Clientes!$B$4:$B$15,MATCH(B10,Clientes!$A$4:$A$15,0)) -> Ferretería El Tornillo | E10: =INDEX(Catalogo_Servicios!$C$4:$C$24,MATCH(C10,Catalogo_Servicios!$A$4:$A$24,0)) -> Declaración mensual de retenciones (D-103) | F10: 0.25 | G10: =Parametros!$B$4 -> 28681 | H10: =INDEX(Clientes!$E$4:$E$15,MATCH(B10,Clientes!$A$4:$A$15,0)) -> 1 | I10: =ROUND(F10*G10*H10,0) -> 7170
A11: 45200 | B11: C03 | C11: S03 | D11: =INDEX(Clientes!$B$4:$B$15,MATCH(B11,Clientes!$A$4:$A$15,0)) -> Clínica Dental Sonrisa | E11: =INDEX(Catalogo_Servicios!$C$4:$C$24,MATCH(C11,Catalogo_Servicios!$A$4:$A$24,0)) -> Declaración mensual de IVA (D-104) | F11: 0.75 | G11: =Parametros!$B$4 -> 28681 | H11: =INDEX(Clientes!$E$4:$E$15,MATCH(B11,Clientes!$A$4:$A$15,0)) -> 1.1 | I11: =ROUND(F11*G11*H11,0) -> 23662
A12: 45200 | B12: C04 | C12: S03 | D12: =INDEX(Clientes!$B$4:$B$15,MATCH(B12,Clientes!$A$4:$A$15,0)) -> Soda y Restaurante Doña Lela | E12: =INDEX(Catalogo_Servicios!$C$4:$C$24,MATCH(C12,Catalogo_Servicios!$A$4:$A$24,0)) -> Declaración mensual de IVA (D-104) | F12: 0.75 | G12: =Parametros!$B$4 -> 28681 | H12: =INDEX(Clientes!$E$4:$E$15,MATCH(B12,Clientes!$A$4:$A$15,0)) -> 1 | I12: =ROUND(F12*G12*H12,0) -> 21511
A13: 45200 | B13: C05 | C13: S01 | D13: =INDEX(Clientes!$B$4:$B$15,MATCH(B13,Clientes!$A$4:$A$15,0)) -> Transportes Rápidos del Valle | E13: =INDEX(Catalogo_Servicios!$C$4:$C$24,MATCH(C13,Catalogo_Servicios!$A$4:$A$24,0)) -> Asesoría contable, financiera y tributaria | F13: 1 | G13: =Parametros!$B$4 -> 28681 | H13: =INDEX(Clientes!$E$4:$E$15,MATCH(B13,Clientes!$A$4:$A$15,0)) -> 1 | I13: =ROUND(F13*G13*H13,0) -> 28681
A14: 45200 | B14: C05 | C14: S03 | D14: =INDEX(Clientes!$B$4:$B$15,MATCH(B14,Clientes!$A$4:$A$15,0)) -> Transportes Rápidos del Valle | E14: =INDEX(Catalogo_Servicios!$C$4:$C$24,MATCH(C14,Catalogo_Servicios!$A$4:$A$24,0)) -> Declaración mensual de IVA (D-104) | F14: 0.75 | G14: =Parametros!$B$4 -> 28681 | H14: =INDEX(Clientes!$E$4:$E$15,MATCH(B14,Clientes!$A$4:$A$15,0)) -> 1 | I14: =ROUND(F14*G14*H14,0) -> 21511
A15: 45200 | B15: C05 | C15: S04 | D15: =INDEX(Clientes!$B$4:$B$15,MATCH(B15,Clientes!$A$4:$A$15,0)) -> Transportes Rápidos del Valle | E15: =INDEX(Catalogo_Servicios!$C$4:$C$24,MATCH(C15,Catalogo_Servicios!$A$4:$A$24,0)) -> Declaración mensual de retenciones (D-103) | F15: 0.25 | G15: =Parametros!$B$4 -> 28681 | H15: =INDEX(Clientes!$E$4:$E$15,MATCH(B15,Clientes!$A$4:$A$15,0)) -> 1 | I15: =ROUND(F15*G15*H15,0) -> 7170
... A724: 46266 | B724: C10 | C724: S05 | D724: =INDEX(Clientes!$B$4:$B$15,MATCH(B724,Clientes!$A$4:$A$15,0)) -> Panadería La Espiga | E724: =INDEX(Catalogo_Servicios!$C$4:$C$24,MATCH(C724,Catalogo_Servicios!$A$4:$A$24,0)) -> Cálculo de planillas y cargas sociales (CCSS/INS) | F724: 8 | G724: =Parametros!$B$4 -> 28681 | H724: =INDEX(Clientes!$E$4:$E$15,MATCH(B724,Clientes!$A$4:$A$15,0)) -> 1 | I724: =ROUND(F724*G724*H724,0) -> 229448

Sheet Declaraciones
A1: Declaraciones presentadas por tipo y mes (conteo desde Facturacion)
A3: Periodo | B3: IVA (D-104) | C3: Retenciones (D-103) | D3: Renta (D-101/D-105) | E3: Planillas CCSS/INS | F3: Informativas (D-151) | G3: TOTAL
A4: 45200 | B4: =COUNTIFS(Facturacion!$A$4:$A$724,$A4,Facturacion!$C$4:$C$724,"S03") -> 8 | C4: =COUNTIFS(Facturacion!$A$4:$A$724,$A4,Facturacion!$C$4:$C$724,"S04") -> 4 | D4: =COUNTIFS(Facturacion!$A$4:$A$724,$A4,Facturacion!$C$4:$C$724,"S06") -> 0 | E4: =COUNTIFS(Facturacion!$A$4:$A$724,$A4,Facturacion!$C$4:$C$724,"S05")+COUNTIFS(Facturacion!$A$4:$A$724,$A4,Facturacion!$C$4:$C$724,"S14") -> 3 | F4: =COUNTIFS(Facturacion!$A$4:$A$724,$A4,Facturacion!$C$4:$C$724,"S13") -> 0 | G4: =SUM(B4:F4) -> 15
A5: 45231 | B5: =COUNTIFS(Facturacion!$A$4:$A$724,$A5,Facturacion!$C$4:$C$724,"S03") -> 8 | C5: =COUNTIFS(Facturacion!$A$4:$A$724,$A5,Facturacion!$C$4:$C$724,"S04") -> 4 | D5: =COUNTIFS(Facturacion!$A$4:$A$724,$A5,Facturacion!$C$4:$C$724,"S06") -> 0 | E5: =COUNTIFS(Facturacion!$A$4:$A$724,$A5,Facturacion!$C$4:$C$724,"S05")+COUNTIFS(Facturacion!$A$4:$A$724,$A5,Facturacion!$C$4:$C$724,"S14") -> 3 | F5: =COUNTIFS(Facturacion!$A$4:$A$724,$A5,Facturacion!$C$4:$C$724,"S13") -> 0 | G5: =SUM(B5:F5) -> 15
A6: 45261 | B6: =COUNTIFS(Facturacion!$A$4:$A$724,$A6,Facturacion!$C$4:$C$724,"S03") -> 8 | C6: =COUNTIFS(Facturacion!$A$4:$A$724,$A6,Facturacion!$C$4:$C$724,"S04") -> 4 | D6: =COUNTIFS(Facturacion!$A$4:$A$724,$A6,Facturacion!$C$4:$C$724,"S06") -> 5 | E6: =COUNTIFS(Facturacion!$A$4:$A$724,$A6,Facturacion!$C$4:$C$724,"S05")+COUNTIFS(Facturacion!$A$4:$A$724,$A6,Facturacion!$C$4:$C$724,"S14") -> 3 | F6: =COUNTIFS(Facturacion!$A$4:$A$724,$A6,Facturacion!$C$4:$C$724,"S13") -> 0 | G6: =SUM(B6:F6) -> 20
A7: 45292 | B7: =COUNTIFS(Facturacion!$A$4:$A$724,$A7,Facturacion!$C$4:$C$724,"S03") -> 8 | C7: =COUNTIFS(Facturacion!$A$4:$A$724,$A7,Facturacion!$C$4:$C$724,"S04") -> 4 | D7: =COUNTIFS(Facturacion!$A$4:$A$724,$A7,Facturacion!$C$4:$C$724,"S06") -> 0 | E7: =COUNTIFS(Facturacion!$A$4:$A$724,$A7,Facturacion!$C$4:$C$724,"S05")+COUNTIFS(Facturacion!$A$4:$A$724,$A7,Facturacion!$C$4:$C$724,"S14") -> 6 | F7: =COUNTIFS(Facturacion!$A$4:$A$724,$A7,Facturacion!$C$4:$C$724,"S13") -> 0 | G7: =SUM(B7:F7) -> 18
A8: 45323 | B8: =COUNTIFS(Facturacion!$A$4:$A$724,$A8,Facturacion!$C$4:$C$724,"S03") -> 8 | C8: =COUNTIFS(Facturacion!$A$4:$A$724,$A8,Facturacion!$C$4:$C$724,"S04") -> 4 | D8: =COUNTIFS(Facturacion!$A$4:$A$724,$A8,Facturacion!$C$4:$C$724,"S06") -> 0 | E8: =COUNTIFS(Facturacion!$A$4:$A$724,$A8,Facturacion!$C$4:$C$724,"S05")+COUNTIFS(Facturacion!$A$4:$A$724,$A8,Facturacion!$C$4:$C$724,"S14") -> 3 | F8: =COUNTIFS(Facturacion!$A$4:$A$724,$A8,Facturacion!$C$4:$C$724,"S13") -> 8 | G8: =SUM(B8:F8) -> 23
A9: 45352 | B9: =COUNTIFS(Facturacion!$A$4:$A$724,$A9,Facturacion!$C$4:$C$724,"S03") -> 8 | C9: =COUNTIFS(Facturacion!$A$4:$A$724,$A9,Facturacion!$C$4:$C$724,"S04") -> 4 | D9: =COUNTIFS(Facturacion!$A$4:$A$724,$A9,Facturacion!$C$4:$C$724,"S06") -> 6 | E9: =COUNTIFS(Facturacion!$A$4:$A$724,$A9,Facturacion!$C$4:$C$724,"S05")+COUNTIFS(Facturacion!$A$4:$A$724,$A9,Facturacion!$C$4:$C$724,"S14") -> 3 | F9: =COUNTIFS(Facturacion!$A$4:$A$724,$A9,Facturacion!$C$4:$C$724,"S13") -> 0 | G9: =SUM(B9:F9) -> 21
A10: 45383 | B10: =COUNTIFS(Facturacion!$A$4:$A$724,$A10,Facturacion!$C$4:$C$724,"S03") -> 8 | C10: =COUNTIFS(Facturacion!$A$4:$A$724,$A10,Facturacion!$C$4:$C$724,"S04") -> 4 | D10: =COUNTIFS(Facturacion!$A$4:$A$724,$A10,Facturacion!$C$4:$C$724,"S06") -> 0 | E10: =COUNTIFS(Facturacion!$A$4:$A$724,$A10,Facturacion!$C$4:$C$724,"S05")+COUNTIFS(Facturacion!$A$4:$A$724,$A10,Facturacion!$C$4:$C$724,"S14") -> 3 | F10: =COUNTIFS(Facturacion!$A$4:$A$724,$A10,Facturacion!$C$4:$C$724,"S13") -> 0 | G10: =SUM(B10:F10) -> 15
A11: 45413 | B11: =COUNTIFS(Facturacion!$A$4:$A$724,$A11,Facturacion!$C$4:$C$724,"S03") -> 8 | C11: =COUNTIFS(Facturacion!$A$4:$A$724,$A11,Facturacion!$C$4:$C$724,"S04") -> 4 | D11: =COUNTIFS(Facturacion!$A$4:$A$724,$A11,Facturacion!$C$4:$C$724,"S06") -> 0 | E11: =COUNTIFS(Facturacion!$A$4:$A$724,$A11,Facturacion!$C$4:$C$724,"S05")+COUNTIFS(Facturacion!$A$4:$A$724,$A11,Facturacion!$C$4:$C$724,"S14") -> 3 | F11: =COUNTIFS(Facturacion!$A$4:$A$724,$A11,Facturacion!$C$4:$C$724,"S13") -> 0 | G11: =SUM(B11:F11) -> 15
A12: 45444 | B12: =COUNTIFS(Facturacion!$A$4:$A$724,$A12,Facturacion!$C$4:$C$724,"S03") -> 8 | C12: =COUNTIFS(Facturacion!$A$4:$A$724,$A12,Facturacion!$C$4:$C$724,"S04") -> 4 | D12: =COUNTIFS(Facturacion!$A$4:$A$724,$A12,Facturacion!$C$4:$C$724,"S06") -> 0 | E12: =COUNTIFS(Facturacion!$A$4:$A$724,$A12,Facturacion!$C$4:$C$724,"S05")+COUNTIFS(Facturacion!$A$4:$A$724,$A12,Facturacion!$C$4:$C$724,"S14") -> 3 | F12: =COUNTIFS(Facturacion!$A$4:$A$724,$A12,Facturacion!$C$4:$C$724,"S13") -> 0 | G12: =SUM(B12:F12) -> 15
A13: 45474 | B13: =COUNTIFS(Facturacion!$A$4:$A$724,$A13,Facturacion!$C$4:$C$724,"S03") -> 8 | C13: =COUNTIFS(Facturacion!$A$4:$A$724,$A13,Facturacion!$C$4:$C$724,"S04") -> 4 | D13: =COUNTIFS(Facturacion!$A$4:$A$724,$A13,Facturacion!$C$4:$C$724,"S06") -> 0 | E13: =COUNTIFS(Facturacion!$A$4:$A$724,$A13,Facturacion!$C$4:$C$724,"S05")+COUNTIFS(Facturacion!$A$4:$A$724,$A13,Facturacion!$C$4:$C$724,"S14") -> 3 | F13: =COUNTIFS(Facturacion!$A$4:$A$724,$A13,Facturacion!$C$4:$C$724,"S13") -> 0 | G13: =SUM(B13:F13) -> 15
A14: 45505 | B14: =COUNTIFS(Facturacion!$A$4:$A$724,$A14,Facturacion!$C$4:$C$724,"S03") -> 8 | C14: =COUNTIFS(Facturacion!$A$4:$A$724,$A14,Facturacion!$C$4:$C$724,"S04") -> 4 | D14: =COUNTIFS(Facturacion!$A$4:$A$724,$A14,Facturacion!$C$4:$C$724,"S06") -> 0 | E14: =COUNTIFS(Facturacion!$A$4:$A$724,$A14,Facturacion!$C$4:$C$724,"S05")+COUNTIFS(Facturacion!$A$4:$A$724,$A14,Facturacion!$C$4:$C$724,"S14") -> 3 | F14: =COUNTIFS(Facturacion!$A$4:$A$724,$A14,Facturacion!$C$4:$C$724,"S13") -> 0 | G14: =SUM(B14:F14) -> 15
A15: 45536 | B15: =COUNTIFS(Facturacion!$A$4:$A$724,$A15,Facturacion!$C$4:$C$724,"S03") -> 8 | C15: =COUNTIFS(Facturacion!$A$4:$A$724,$A15,Facturacion!$C$4:$C$724,"S04") -> 4 | D15: =COUNTIFS(Facturacion!$A$4:$A$724,$A15,Facturacion!$C$4:$C$724,"S06") -> 0 | E15: =COUNTIFS(Facturacion!$A$4:$A$724,$A15,Facturacion!$C$4:$C$724,"S05")+COUNTIFS(Facturacion!$A$4:$A$724,$A15,Facturacion!$C$4:$C$724,"S14") -> 3 | F15: =COUNTIFS(Facturacion!$A$4:$A$724,$A15,Facturacion!$C$4:$C$724,"S13") -> 0 | G15: =SUM(B15:F15) -> 15
... A39: 46266 | B39: =COUNTIFS(Facturacion!$A$4:$A$724,$A39,Facturacion!$C$4:$C$724,"S03") -> 8 | C39: =COUNTIFS(Facturacion!$A$4:$A$724,$A39,Facturacion!$C$4:$C$724,"S04") -> 4 | D39: =COUNTIFS(Facturacion!$A$4:$A$724,$A39,Facturacion!$C$4:$C$724,"S06") -> 0 | E39: =COUNTIFS(Facturacion!$A$4:$A$724,$A39,Facturacion!$C$4:$C$724,"S05")+COUNTIFS(Facturacion!$A$4:$A$724,$A39,Facturacion!$C$4:$C$724,"S14") -> 3 | F39: =COUNTIFS(Facturacion!$A$4:$A$724,$A39,Facturacion!$C$4:$C$724,"S13") -> 0 | G39: =SUM(B39:F39) -> 15

Sheet Catalogo_Servicios
A1: Catálogo de servicios según el tarifario de honorarios mínimos del Colegio de Contadores Públicos de Costa Rica (CCPA)
A2: Categorías I a VI del tarifario. Honorarios estándar = horas estándar x tarifa horaria de la hoja Parametros.
A3: Cód. | B3: Cat. CCPA | C3: Servicio | D3: Base de cobro CCPA | E3: Frecuencia | F3: Horas mínimas CCPA | G3: Horas estándar usadas | H3: Honorario estándar (₡ sin IVA) | I3: Honorario con IVA (₡) | J3: ¿Lo presta ContaFacil? | K3: Origen de las horas | L3: Facturado en 36 meses (₡)
A4: N01 | B4: I | C4: Auditoría de estados financieros - entidad privada no regulada | D4: Tarifa horaria; opinión anual mínimo 80 horas | E4: Anual | F4: 80 | G4: 80 | H4: =G4*Parametros!$B$4 -> 2294480 | I4: =H4*(1+Parametros!$B$5) -> 2592762.4 | J4: No | K4: CCPA (mínimo oficial) | L4: =SUMIFS(Facturacion!$I$4:$I$724,Facturacion!$C$4:$C$724,A4) -> 0
A5: N02 | B5: I | C5: Auditoría de estados financieros - entidad pública o regulada | D5: Tarifa horaria; opinión anual mínimo 100 horas | E5: Anual | F5: 100 | G5: 100 | H5: =G5*Parametros!$B$4 -> 2868100 | I5: =H5*(1+Parametros!$B$5) -> 3240953 | J5: No | K5: CCPA (mínimo oficial) | L5: =SUMIFS(Facturacion!$I$4:$I$724,Facturacion!$C$4:$C$724,A5) -> 0
A6: S01 | B6: II | C6: Asesoría contable, financiera y tributaria | D6: Tarifa horaria, sin mínimo de horas | E6: Eventual | F6: sin mínimo | G6: 1 | H6: =G6*Parametros!$B$4 -> 28681 | I6: =H6*(1+Parametros!$B$5) -> 32409.53 | J6: Sí | K6: CCPA (tarifa); 1 h = unidad | L6: =SUMIFS(Facturacion!$I$4:$I$724,Facturacion!$C$4:$C$724,A6) -> 902019
A7: S02 | B7: II | C7: Estados financieros mensuales | D7: Tarifa horaria sin mínimo; referencia de 3 horas/mes para pymes | E7: Mensual | F7: sin mínimo | G7: 3 | H7: =G7*Parametros!$B$4 -> 86043 | I7: =H7*(1+Parametros!$B$5) -> 97228.59 | J7: Sí | K7: Fuente secundaria (3 h/mes) | L7: =SUMIFS(Facturacion!$I$4:$I$724,Facturacion!$C$4:$C$724,A7) -> 6424544
A8: S03 | B8: II | C8: Declaración mensual de IVA (D-104) | D8: Tarifa horaria sin mínimo | E8: Mensual | F8: sin mínimo | G8: 0.75 | H8: =G8*Parametros!$B$4 -> 21510.75 | I8: =H8*(1+Parametros!$B$5) -> 24307.147 | J8: Sí | K8: Supuesto del equipo | L8: =SUMIFS(Facturacion!$I$4:$I$724,Facturacion!$C$4:$C$724,A8) -> 6547932
A9: S04 | B9: II | C9: Declaración mensual de retenciones (D-103) | D9: Tarifa horaria sin mínimo | E9: Mensual | F9: sin mínimo | G9: 0.25 | H9: =G9*Parametros!$B$4 -> 7170.25 | I9: =H9*(1+Parametros!$B$5) -> 8102.3825 | J9: Sí | K9: Supuesto del equipo (S03+S04 = 1 h) | L9: =SUMIFS(Facturacion!$I$4:$I$724,Facturacion!$C$4:$C$724,A9) -> 1032480
A10: S05 | B10: II | C10: Cálculo de planillas y cargas sociales (CCSS/INS) | D10: Tarifa horaria sin mínimo; base 3 h + 0,5 h por empleado | E10: Mensual | F10: sin mínimo | G10: 3 | H10: =G10*Parametros!$B$4 -> 86043 | I10: =H10*(1+Parametros!$B$5) -> 97228.59 | J10: Sí | K10: Fuente secundaria (3 h base); 0,5 h/empleado es supuesto | L10: =SUMIFS(Facturacion!$I$4:$I$724,Facturacion!$C$4:$C$724,A10) -> 36611327
A11: S06 | B11: II | C11: Declaración anual de renta (D-101 / D-105) | D11: Tarifa horaria sin mínimo | E11: Anual | F11: sin mínimo | G11: 1.5 | H11: =G11*Parametros!$B$4 -> 43021.5 | I11: =H11*(1+Parametros!$B$5) -> 48614.295 | J11: Sí | K11: Supuesto del equipo | L11: =SUMIFS(Facturacion!$I$4:$I$724,Facturacion!$C$4:$C$724,A11) -> 1629453
A12: S07 | B12: II | C12: Estados financieros anuales / cierre fiscal | D12: Tarifa horaria sin mínimo; referencia de 6 horas | E12: Anual | F12: sin mínimo | G12: 6 | H12: =G12*Parametros!$B$4 -> 172086 | I12: =H12*(1+Parametros!$B$5) -> 194457.18 | J12: Sí | K12: Fuente secundaria (6 h) | L12: =SUMIFS(Facturacion!$I$4:$I$724,Facturacion!$C$4:$C$724,A12) -> 1548774
A13: S13 | B13: II | C13: Declaración informativa anual (D-151) | D13: Tarifa horaria sin mínimo | E13: Anual | F13: sin mínimo | G13: 0.5 | H13: =G13*Parametros!$B$4 -> 14340.5 | I13: =H13*(1+Parametros!$B$5) -> 16204.765 | J13: Sí | K13: Supuesto del equipo | L13: =SUMIFS(Facturacion!$I$4:$I$724,Facturacion!$C$4:$C$724,A13) -> 348486
A14: S14 | B14: II | C14: Conciliación anual de planillas (INS/CCSS) | D14: Tarifa horaria sin mínimo | E14: Anual | F14: sin mínimo | G14: 2 | H14: =G14*Parametros!$B$4 -> 57362 | I14: =H14*(1+Parametros!$B$5) -> 64819.06 | J14: Sí | K14: Supuesto del equipo | L14: =SUMIFS(Facturacion!$I$4:$I$724,Facturacion!$C$4:$C$724,A14) -> 516258
A15: N03 | B15: III | C15: Peritaje extrajudicial y arbitraje | D15: Tarifa horaria; mínimo 18 horas | E15: Eventual | F15: 18 | G15: 18 | H15: =G15*Parametros!$B$4 -> 516258 | I15: =H15*(1+Parametros!$B$5) -> 583371.54 | J15: No | K15: CCPA (mínimo oficial) | L15: =SUMIFS(Facturacion!$I$4:$I$724,Facturacion!$C$4:$C$724,A15) -> 0
A16: S08 | B16: IV.a | C16: Certificación de ingresos y estudios generales | D16: Tarifa horaria; mínimo 3 horas | E16: Eventual | F16: 3 | G16: 3 | H16: =G16*Parametros!$B$4 -> 86043 | I16: =H16*(1+Parametros!$B$5) -> 97228.59 | J16: Sí | K16: CCPA (mínimo oficial) | L16: =SUMIFS(Facturacion!$I$4:$I$724,Facturacion!$C$4:$C$724,A16) -> 451725
A17: S09 | B17: IV.b | C17: Certificación para PYME / Régimen simplificado (MEIC) | D17: 5% del ingreso neto mensual promedio; mínimo 3 horas | E17: Eventual | F17: 3 | G17: 3 | H17: =G17*Parametros!$B$4 -> 86043 | I17: =H17*(1+Parametros!$B$5) -> 97228.59 | J17: Sí | K17: CCPA (se usa el mínimo de horas) | L17: =SUMIFS(Facturacion!$I$4:$I$724,Facturacion!$C$4:$C$724,A17) -> 189294
A18: N04 | B18: IV.c | C18: Certificación para entidades sin fines de lucro | D18: 2,5% del superávit mensual promedio; mínimo 3 horas | E18: Eventual | F18: 3 | G18: 3 | H18: =G18*Parametros!$B$4 -> 86043 | I18: =H18*(1+Parametros!$B$5) -> 97228.59 | J18: No | K18: CCPA (mínimo oficial) | L18: =SUMIFS(Facturacion!$I$4:$I$724,Facturacion!$C$4:$C$724,A18) -> 0
A19: N05 | B19: IV.e | C19: Certificación de saldo deudor bancario | D19: Mitad de la tarifa horaria por certificación (mín. 100 al mes) | E19: Eventual | F19: 0.5 | G19: 0.5 | H19: =G19*Parametros!$B$4 -> 14340.5 | I19: =H19*(1+Parametros!$B$5) -> 16204.765 | J19: No | K19: CCPA (≈ ¢11 347,86 en 2021) | L19: =SUMIFS(Facturacion!$I$4:$I$724,Facturacion!$C$4:$C$724,A19) -> 0
A20: S12 | B20: V | C20: Estudio de pre-factibilidad, factibilidad o flujo de caja | D20: 5% del flujo de caja promedio; mínimo 10 horas | E20: Eventual | F20: 10 | G20: 10 | H20: =G20*Parametros!$B$4 -> 286810 | I20: =H20*(1+Parametros!$B$5) -> 324095.3 | J20: Sí | K20: CCPA (se usa el mínimo de horas) | L20: =SUMIFS(Facturacion!$I$4:$I$724,Facturacion!$C$4:$C$724,A20) -> 0
A21: S15 | B21: VI.a | C21: Certificación de estados financieros (consistencia con registros) | D21: Tarifa horaria; mínimo 5 horas | E21: Eventual | F21: 5 | G21: 5 | H21: =G21*Parametros!$B$4 -> 143405 | I21: =H21*(1+Parametros!$B$5) -> 162047.65 | J21: Sí | K21: CCPA (mínimo oficial) | L21: =SUMIFS(Facturacion!$I$4:$I$724,Facturacion!$C$4:$C$724,A21) -> 0
A22: S10 | B22: VI.b | C22: Certificación de hechos específicos (solvencia, capital, pasivos) | D22: Tarifa horaria; mínimo 5 horas | E22: Eventual | F22: 5 | G22: 5 | H22: =G22*Parametros!$B$4 -> 143405 | I22: =H22*(1+Parametros!$B$5) -> 162047.65 | J22: Sí | K22: CCPA (mínimo oficial) | L22: =SUMIFS(Facturacion!$I$4:$I$724,Facturacion!$C$4:$C$724,A22) -> 0
A23: S11 | B23: VI.c | C23: Estudio especial (control interno, análisis financiero) | D23: Tarifa horaria; mínimo 5 horas | E23: Eventual | F23: 5 | G23: 5 | H23: =G23*Parametros!$B$4 -> 143405 | I23: =H23*(1+Parametros!$B$5) -> 162047.65 | J23: Sí | K23: CCPA (mínimo oficial) | L23: =SUMIFS(Facturacion!$I$4:$I$724,Facturacion!$C$4:$C$724,A23) -> 150575
A24: S16 | B24: VI.d | C24: Otros trabajos profesionales no contemplados | D24: Tarifa horaria; mínimo 3 horas | E24: Eventual | F24: 3 | G24: 3 | H24: =G24*Parametros!$B$4 -> 86043 | I24: =H24*(1+Parametros!$B$5) -> 97228.59 | J24: Sí | K24: CCPA (mínimo oficial) | L24: =SUMIFS(Facturacion!$I$4:$I$724,Facturacion!$C$4:$C$724,A24) -> 184992
A26: Gris = servicios del tarifario que ContaFacil no presta (auditoría, peritajes, certificaciones bancarias, etc.). Se incluyen para que el catálogo refleje el tarifario completo.

Sheet Parametros
A1: Parámetros del cálculo de honorarios
A3: Parámetro | B3: Valor | C3: Fuente / nota
A4: Tarifa horaria mínima usada (₡, sin IVA) | B4: 28681 | C4: Fuente secundaria (Consultores Jiménez, tarifas 2026) la cita como tarifa mínima del CCPA vigente desde dic-2022. VERIFICAR en ccpa.or.cr antes de entregar.
A5: IVA | B5: 0.13 | C5: Tasa general de IVA en Costa Rica. Los ingresos del pronóstico se miden SIN IVA.
A6: Tarifa horaria en el PDF oficial THPMCPA-14-2021 (₡) | B6: 22695.71 | C6: PDF del CCPA publicado en La Gaceta N° 188 (30-sep-2021). Solo referencia.
A7: Vigencia de la tarifa usada | B7: dic-2022 | C7: Según la misma fuente secundaria; el CCPA actualiza la tarifa por acuerdo.
A9: Para cambiar la tarifa, edite la celda B4: todos los montos de Facturacion, Detalle_Clientes e Ingresos se recalculan.

Sheet Clientes
A1: Catálogo de clientes (ficticios)
A3: Código | B3: Cliente | C3: Tipo de contribuyente | D3: Servicios contratados | E3: Factor sobre tarifa mínima | F3: Inicio de la relación
A4: C01 | B4: Distribuidora Los Andes S.A. | C4: Persona jurídica | D4: Contabilidad + IVA + retenciones + planilla (volumen alto) | E4: 1 | F4: 45200
A5: C02 | B5: Ferretería El Tornillo | C5: Persona jurídica | D5: Estados financieros mensuales + IVA + retenciones | E5: 1 | F5: 45200
A6: C03 | B6: Clínica Dental Sonrisa | C6: Persona física con act. lucrativa | D6: IVA + renta | E6: 1.1 | F6: 45200
A7: C04 | B7: Soda y Restaurante Doña Lela | C7: Persona física con act. lucrativa | D7: IVA + renta | E7: 1 | F7: 45200
A8: C05 | B8: Transportes Rápidos del Valle | C8: Persona jurídica | D8: IVA + retenciones + planilla pequeña | E8: 1 | F8: 45200
A9: C06 | B9: Boutique Luna Nueva | C9: Persona física con act. lucrativa | D9: Régimen simplificado: renta + certificaciones | E9: 1.15 | F9: 45200
A10: C07 | B10: Taller Mecánico Hermanos Mora | C10: Persona jurídica | D10: IVA + renta | E10: 1 | F10: 45200
A11: C08 | B11: Agroservicios Cartago | C11: Persona jurídica | D11: IVA + retenciones + renta | E11: 1 | F11: 45200
A12: C09 | B12: Estudio Fotográfico Lumière | C12: Persona física con act. lucrativa | D12: Régimen simplificado: renta + certificaciones | E12: 1.1 | F12: 45200
A13: C10 | B13: Panadería La Espiga | C13: Persona jurídica | D13: IVA + planilla pequeña | E13: 1 | F13: 45200
A14: C11 | B14: Consultores TIC Pura Vida | C14: Persona jurídica | D14: Contabilidad básica + renta + certificaciones | E14: 1 | F14: 45323
A15: C12 | B15: Veterinaria Mascotas Felices | C15: Persona física con act. lucrativa | D15: Régimen simplificado: renta + certificaciones | E15: 1.05 | F15: 45505

Sheet Supuestos_Fuentes
A1: Supuestos y fuentes
A3: DATOS FICTICIOS: ContaFacil no puede entregar su historial por confidencialidad. Los ingresos se simularon con las reglas de abajo.
A4: - 36 meses (oct-2023 a sep-2026), 12 clientes con nombres inventados. Ingresos totales entre ~₡1,3 M y ~₡2,0 M por mes, sin IVA.
A5: - Cada ingreso = horas x tarifa horaria mínima del CCPA x factor del cliente (1,00 a 1,15). Hay una línea por cliente, servicio y mes en la hoja Facturacion.
A6: - Cliente C01 (el mayor): contabilidad, IVA, retenciones y planilla. La planilla varía con el número de empleados (3 h base + 0,5 h por empleado), por eso su pago es variable (≈ ₡0,67 M a ₡1,15 M, con tope de ₡1,2 M).
A7: - Estacionalidad: picos en diciembre y marzo (declaración anual de renta y cierres), actividad extra en enero (planillas anuales) y febrero (informativas); valle en mitad de año.
A8: - Tendencia creciente por entrada de dos clientes (C11 en feb-2024, C12 en ago-2024), más empleados en C01 y un pequeño aumento de horas por cliente.
A9: - Servicios eventuales (certificaciones, asesorías, estudios) aparecen al azar y agregan ruido.
A10: - Declaraciones: unas 15 al mes en promedio (IVA, retenciones, planillas) más las anuales en sus meses.
A11: - Las horas estándar marcadas 'Supuesto del equipo' en el catálogo NO provienen del CCPA; justifíquenlas con el gerente en la entrevista.
A12: - Fechas de renta supuestas: período ordinario con presentación en diciembre; período especial con presentación en marzo. Verificar con el calendario de Hacienda.
A14: FUENTES
... A18: - CRHoy (27-dic-2024). Sala IV publica resolución que mantiene tarifas mínimas para el Colegio de Contadores: https://crhoy.com/nacionales/sala-iv-publica-resolucion-que-mantiene-tarifas-minimas-para-colegio-de-contadores/
